apotek_tools/__init__.py
apotek_tools/__main__.py
apotek_tools/api.py
apotek_tools/cli.py
apotek_tools/config.py
apotek_tools/excel_generator.py
apotek_tools/fetcher.py
apotek_tools-0.1.0.dist-info/METADATA
apotek_tools-0.1.0.dist-info/WHEEL
apotek_tools-0.1.0.dist-info/entry_points.txt
apotek_tools-0.1.0.dist-info/top_level.txt
apotek_tools-0.1.0.dist-info/RECORD
