Metadata-Version: 2.4
Name: apotek-tools
Version: 0.1.0
Summary: Tools for Apotek price list management
Requires-Python: >=3.8
Requires-Dist: requests
Requires-Dist: pandas
Requires-Dist: openpyxl
Requires-Dist: click
Requires-Dist: rich
